app/callbacks.py
app/main.py
sqlglot_cli-0.1.0.dist-info/METADATA
sqlglot_cli-0.1.0.dist-info/WHEEL
sqlglot_cli-0.1.0.dist-info/entry_points.txt
sqlglot_cli-0.1.0.dist-info/RECORD
