Metadata-Version: 2.1
Name: sqlglot-cli
Version: 0.1.0
Summary: CLI wrapper around sqlglot
Author: Michael Harris
Author-email: mharris@definite.app
Requires-Python: >=3.12,<4.0
Classifier: Programming Language :: Python :: 3
Classifier: Programming Language :: Python :: 3.12
Provides-Extra: rich
Provides-Extra: rs
Requires-Dist: rich (>=13.9.3,<14.0.0) ; extra == "rich"
Requires-Dist: sqlglot (>=25.28.0,<26.0.0)
Requires-Dist: sqlglotrs (>=0.2.13,<0.3.0) ; extra == "rs"
Requires-Dist: typer (>=0.12.5,<0.13.0)
